dashboard_builder/.DS_Store
dashboard_builder/__init__.py
dashboard_builder/components/.DS_Store
dashboard_builder/components/__init__.py
dashboard_builder/components/inputs.py
dashboard_builder/components/layouts.py
dashboard_builder/components/outputs.py
dashboard_builder/components/templates/.DS_Store
dashboard_builder/components/templates/formgroups/formgroup.j2
dashboard_builder/components/templates/inputs/inputdropdown.j2
dashboard_builder/components/templates/inputs/inputradio.j2
dashboard_builder/components/templates/inputs/inputslider_categorical.j2
dashboard_builder/components/templates/inputs/inputslider_numerical.j2
dashboard_builder/components/templates/inputs/textinput.j2
dashboard_builder/components/templates/layouts/expanderlayout.j2
dashboard_builder/components/templates/outputs/outputchart_altair.j2
dashboard_builder/components/templates/outputs/outputchart_matplotlib.j2
dashboard_builder/components/templates/outputs/outputchart_plotly.j2
dashboard_builder/components/templates/outputs/outputimage.j2
dashboard_builder/components/templates/outputs/outputmarkdown.j2
dashboard_builder/components/templates/outputs/outputtable_html.j2
dashboard_builder/components/templates/outputs/outputtext.j2
dashboard_builder/dashboard_templates/base.j2
dashboard_builder/dashboard_templates/base_nosidebar.j2
dashboard_builder/managers.py
dashboard_builder/outputs.py
dashboard_builder/theme_utils.py
dashboard_builder/themes.py
dashboard_builder/utils.py
dashboard_builder-0.4.7.dist-info/METADATA
dashboard_builder-0.4.7.dist-info/WHEEL
dashboard_builder-0.4.7.dist-info/RECORD
