Metadata-Version: 2.1
Name: dashboard-builder
Version: 0.4.7
Summary: A lightweight dashboard builder for data scientists.
Author: Hants Williams
Author-email: hantsawilliams@gmail.com
Requires-Python: >=3.9,<3.13
Classifier: Programming Language :: Python :: 3
Classifier: Programming Language :: Python :: 3.9
Classifier: Programming Language :: Python :: 3.10
Classifier: Programming Language :: Python :: 3.11
Requires-Dist: flask (>=2.3.3,<3.0.0)
Requires-Dist: markdown (>=3.4.4,<4.0.0)
Requires-Dist: matplotlib (>=3.8.0,<4.0.0)
Requires-Dist: pandas (>=2.1.1,<3.0.0)
Requires-Dist: plotly (>=5.17.0,<6.0.0)
Requires-Dist: requests (>=2.31.0,<3.0.0)
